{
    "type": "object",
    "properties": {
        "contentVersion": {
            "type": "string"
        },
        "source": {
            "type": "string"
        },
        "summaryId": {
            "required": true,
            "type": "string"
        },
        "volumeId": {
            "required": true,
            "type": "string"
        },
        "prettyPrint": {
            "type": "boolean",
            "default": true
        },
        "quotaUser": {
            "type": "string"
        },
        "userIp": {
            "type": "string"
        }
    }
}